CaptchaGenerator/CaptchaGenerator.py
CaptchaGenerator-1.1.6.dist-info/METADATA
CaptchaGenerator-1.1.6.dist-info/WHEEL
CaptchaGenerator-1.1.6.dist-info/top_level.txt
CaptchaGenerator-1.1.6.dist-info/RECORD
